[
  {
    "name": "alpine",
    "version": "3.19",
    "url": "https://github.com/Ernest1338/nspawn-registry/releases/download/alpine/alpine-v3.19.tar.gz"
  },
  {
    "name": "arch",
    "version": "1.0",
    "url": "http://localhost:8080/alpine.tar.gz"
  },
  {
    "name": "debian",
    "version": "1.0",
    "url": "http://localhost:8080/alpine.tar.gz"
  },
  {
    "name": "ubuntu",
    "version": "1.0",
    "url": "http://localhost:8080/alpine.tar.gz"
  },
  {
    "name": "nginx",
    "version": "1.0",
    "url": "http://localhost:8080/alpine.tar.gz"
  }
]
